sbom2doc/__init__.py
sbom2doc/cli.py
sbom2doc/generator.py
sbom2doc/version.py
sbom2doc/docbuilder/__init__.py
sbom2doc/docbuilder/consolebuilder.py
sbom2doc/docbuilder/docbuilder.py
sbom2doc/docbuilder/htmlbuilder.py
sbom2doc/docbuilder/jsonbuilder.py
sbom2doc/docbuilder/markdownbuilder.py
sbom2doc/docbuilder/pdfbuilder.py
sbom2doc/docbuilder/spreadsheetbuilder.py
sbom2doc-0.6.2.dist-info/LICENSE
sbom2doc-0.6.2.dist-info/METADATA
sbom2doc-0.6.2.dist-info/WHEEL
sbom2doc-0.6.2.dist-info/entry_points.txt
sbom2doc-0.6.2.dist-info/top_level.txt
sbom2doc-0.6.2.dist-info/RECORD
