Metadata-Version: 2.1
Name: sbom2doc
Version: 0.6.2
Summary: SBOM documentation tool
Home-page: https://github.com/anthonyharrison/sbom2doc
Author: Anthony Harrison
Author-email: anthony.p.harrison@gmail.com
Maintainer: Anthony Harrison
Maintainer-email: anthony.p.harrison@gmail.com
License: Apache-2.0
Keywords: documentation,tools,SBOM,DevSecOps,SPDX,CycloneDX
Classifier: Development Status :: 3 - Alpha
Classifier: Intended Audience :: Developers
Classifier: License :: OSI Approved :: Apache Software License
Classifier: Natural Language :: English
Classifier: Operating System :: OS Independent
Classifier: Programming Language :: Python :: 3.7
Classifier: Programming Language :: Python :: 3.8
Classifier: Programming Language :: Python :: 3.9
Classifier: Programming Language :: Python :: 3.10
Classifier: Programming Language :: Python :: 3.11
Classifier: Programming Language :: Python :: Implementation :: CPython
Classifier: Programming Language :: Python :: Implementation :: PyPy
Requires-Python: >=3.7
License-File: LICENSE
Requires-Dist: lib4sbom (>=0.8.7)
Requires-Dist: openpyxl
Requires-Dist: packageurl-python
Requires-Dist: reportlab (>=4.4.0)
Requires-Dist: requests
Requires-Dist: rich
